setup.py
GoldenXp/GoldenXp.py
GoldenXp/__init__.py
GoldenXp.egg-info/PKG-INFO
GoldenXp.egg-info/SOURCES.txt
GoldenXp.egg-info/dependency_links.txt
GoldenXp.egg-info/top_level.txt